{
  "kind": "node-graph",
  "version": 1,
  "title": "Patch: Load Image From Assets → Image to Client",
  "purpose": "体验 asset:<id> 引用 + client 侧 MediaEngine(showImage) 播放链路（Graph-driven Patch）",
  "howTo": [
    "1) 打开 client。",
    "2) manager Node Graph 点 ▶ Start。",
    "3) 先在 Assets Manager 上传图片，然后在 Load Image From Assets 里选择该图片。",
    "4) 通过 `Image to Client(Deploy) → Client(In)` 指定播放目标。"
  ],
  "graph": {
    "nodes": [
      {
        "id": "node-client",
        "type": "client-object",
        "position": { "x": 980, "y": 320 },
        "config": { "clientId": "" },
        "inputValues": { "index": 1, "range": 1, "random": false },
        "outputValues": {}
      },
      {
        "id": "node-load-image",
        "type": "load-image-from-assets",
        "position": { "x": 120, "y": 260 },
        "config": { "assetId": "" },
        "inputValues": {},
        "outputValues": {}
      },
      {
        "id": "node-image-out",
        "type": "image-out",
        "position": { "x": 520, "y": 260 },
        "config": {},
        "inputValues": {},
        "outputValues": {}
      }
    ],
    "connections": [
      {
        "id": "conn-image-out",
        "sourceNodeId": "node-load-image",
        "sourcePortId": "ref",
        "targetNodeId": "node-image-out",
        "targetPortId": "in"
      },
      {
        "id": "conn-deploy",
        "sourceNodeId": "node-image-out",
        "sourcePortId": "cmd",
        "targetNodeId": "node-client",
        "targetPortId": "in"
      }
    ]
  }
}
