{
  "type": "proc-visual-scene-box",
  "label": "Visual Scene-Box",
  "category": "Processors",
  "inputs": [
    { "id": "enabled", "label": "Enabled", "type": "boolean", "defaultValue": true }
  ],
  "outputs": [{ "id": "cmd", "label": "Cmd", "type": "command" }],
  "configSchema": [
    { "key": "enabled", "label": "Enabled", "type": "boolean", "defaultValue": true }
  ],
  "runtime": {
    "kind": "command",
    "command": {
      "action": "visualSceneBox",
      "payload": {
        "enabled": {
          "kind": "booleanFromThreshold",
          "inputKey": "enabled",
          "configKey": "enabled",
          "threshold": 0.5,
          "default": true
        }
      }
    }
  }
}
